linkedin_discord_bot/__init__.py
linkedin_discord_bot/db.py
linkedin_discord_bot/exceptions.py
linkedin_discord_bot/logging.py
linkedin_discord_bot/models.py
linkedin_discord_bot/settings.py
linkedin_discord_bot/utils.py
linkedin_discord_bot/cli/__init__.py
linkedin_discord_bot/cli/__main__.py
linkedin_discord_bot/cli/bot.py
linkedin_discord_bot/cli/jobs.py
linkedin_discord_bot/cli/main.py
linkedin_discord_bot/cli/scraper.py
linkedin_discord_bot/cli/version.py
linkedin_discord_bot/discord/__init__.py
linkedin_discord_bot/discord/cogs/__init__.py
linkedin_discord_bot/discord/cogs/commands/__init__.py
linkedin_discord_bot/discord/cogs/commands/job.py
linkedin_discord_bot/discord/cogs/commands/query.py
linkedin_discord_bot/discord/cogs/tasks/__init__.py
linkedin_discord_bot/discord/cogs/tasks/scraper.py
linkedin_discord_bot/scraper/__init__.py
linkedin_discord_bot/scraper/callbacks.py
linkedin_discord_bot-0.1.4.dist-info/METADATA
linkedin_discord_bot-0.1.4.dist-info/WHEEL
linkedin_discord_bot-0.1.4.dist-info/entry_points.txt
linkedin_discord_bot-0.1.4.dist-info/licenses/LICENSE.md
linkedin_discord_bot-0.1.4.dist-info/RECORD
