Metadata-Version: 2.4
Name: linkedin-discord-bot
Version: 0.1.4
Summary: A Discord bot that posts LinkedIn job postings
Project-URL: homepage, https://github.com/IAmSkweetis/linkedin-discord-bot
Project-URL: source, https://github.com/IAmSkweetis/linkedin-discord-bot
Project-URL: docs, https://github.com/IAmSkweetis/linkedin-discord-bot/README.md
Project-URL: issues, https://github.com/IAmSkweetis/linkedin-discord-bot/issues
License-Expression: MIT
License-File: LICENSE.md
Requires-Python: >=3.12
Requires-Dist: linkedin-jobs-scraper>=5.0.2
Requires-Dist: prettytable>=3.16.0
Requires-Dist: psycopg[binary]>=3.2.6
Requires-Dist: py-cord>=2.6.1
Requires-Dist: pydantic-settings>=2.8.1
Requires-Dist: pydantic>=2.11.3
Requires-Dist: sqlalchemy>=2.0.40
Requires-Dist: sqlmodel>=0.0.24
Requires-Dist: typer>=0.15.2
Requires-Dist: typing-extensions>=4.13.2
